preprocess_trr/__init__.py
preprocess_trr/text_preprocess.py
preprocess_trr/data/contractions.json
preprocess_trr-0.1.dist-info/licenses/LICENSE
preprocess_trr-0.1.dist-info/METADATA
preprocess_trr-0.1.dist-info/WHEEL
preprocess_trr-0.1.dist-info/top_level.txt
preprocess_trr-0.1.dist-info/RECORD
