Metadata-Version: 2.4
Name: preprocess_trr
Version: 0.1
Summary: This is a text preprocessing package
Author: Vladyslav Borsh
Author-email: test@udemy.com
Classifier: Programming Language :: Python :: 3
Classifier: License :: OSI Approved :: MIT License
Classifier: Operating System :: OS Independent
Requires-Python: >=3.7
License-File: LICENSE
Dynamic: author
Dynamic: author-email
Dynamic: classifier
Dynamic: description
Dynamic: description-content-type
Dynamic: license-file
Dynamic: requires-python
Dynamic: summary
